panther/__init__.py
panther/_load_configs.py
panther/_utils.py
panther/app.py
panther/authentications.py
panther/background_tasks.py
panther/base_request.py
panther/base_websocket.py
panther/caching.py
panther/configs.py
panther/events.py
panther/exceptions.py
panther/file_handler.py
panther/generics.py
panther/logging.py
panther/main.py
panther/pagination.py
panther/permissions.py
panther/request.py
panther/response.py
panther/routings.py
panther/serializer.py
panther/status.py
panther/test.py
panther/throttling.py
panther/utils.py
panther/websocket.py
panther/cli/__init__.py
panther/cli/create_project_command.py
panther/cli/create_user_command.py
panther/cli/main.py
panther/cli/monitor_command.py
panther/cli/run_command.py
panther/cli/template.py
panther/cli/utils.py
panther/db/__init__.py
panther/db/connections.py
panther/db/cursor.py
panther/db/models.py
panther/db/utils.py
panther/db/queries/__init__.py
panther/db/queries/base_queries.py
panther/db/queries/mongodb_queries.py
panther/db/queries/pantherdb_queries.py
panther/db/queries/queries.py
panther/middlewares/__init__.py
panther/middlewares/base.py
panther/middlewares/cors.py
panther/middlewares/monitoring.py
panther/openapi/__init__.py
panther/openapi/schemas.py
panther/openapi/urls.py
panther/openapi/utils.py
panther/openapi/views.py
panther/openapi/templates/rapidoc.html
panther/openapi/templates/redoc.html
panther/openapi/templates/scalar.html
panther/openapi/templates/spotlight.html
panther/openapi/templates/swagger.html
panther/panel/__init__.py
panther/panel/authentications.py
panther/panel/middlewares.py
panther/panel/permissions.py
panther/panel/urls.py
panther/panel/utils.py
panther/panel/views.py
panther/panel/templates/base.html
panther/panel/templates/create.html
panther/panel/templates/create.js
panther/panel/templates/detail.html
panther/panel/templates/home.html
panther/panel/templates/home.js
panther/panel/templates/login.html
panther/panel/templates/sidebar.html
panther-5.2.0.dist-info/licenses/LICENSE
panther-5.2.0.dist-info/METADATA
panther-5.2.0.dist-info/WHEEL
panther-5.2.0.dist-info/entry_points.txt
panther-5.2.0.dist-info/top_level.txt
panther-5.2.0.dist-info/RECORD
