Metadata-Version: 2.4
Name: panther
Version: 5.2.0
Summary: Fast & Friendly, Web Framework For Building Async APIs
Home-page: https://github.com/alirn76/panther
Author: Ali RajabNezhad
Author-email: alirn76@yahoo.com
License: BSD-3-Clause license
Classifier: Operating System :: OS Independent
Classifier: Programming Language :: Python :: 3.10
Classifier: Programming Language :: Python :: 3.11
Classifier: Programming Language :: Python :: 3.12
Classifier: Programming Language :: Python :: 3.13
Classifier: Programming Language :: Python :: 3.14
Requires-Python: >=3.10
License-File: LICENSE
Requires-Dist: pantherdb~=2.3.3
Requires-Dist: orjson~=3.11.3
Requires-Dist: pydantic~=2.12.3
Requires-Dist: rich~=14.2.0
Requires-Dist: uvicorn>=0.21.0
Requires-Dist: pytz~=2025.2
Requires-Dist: Jinja2~=3.1.6
Requires-Dist: simple-ulid~=1.0.0
Requires-Dist: httptools~=0.7.1
Provides-Extra: full
Requires-Dist: redis==6.2.0; extra == "full"
Requires-Dist: motor~=3.7.1; extra == "full"
Requires-Dist: ipython~=9.4.0; extra == "full"
Requires-Dist: python-jose~=3.5.0; extra == "full"
Requires-Dist: websockets~=15.0.1; extra == "full"
Requires-Dist: cryptography~=45.0.5; extra == "full"
Requires-Dist: watchfiles~=1.1.0; extra == "full"
Dynamic: author
Dynamic: author-email
Dynamic: classifier
Dynamic: description
Dynamic: description-content-type
Dynamic: home-page
Dynamic: license
Dynamic: license-file
Dynamic: provides-extra
Dynamic: requires-dist
Dynamic: requires-python
Dynamic: summary
